tests/__init__.py
tests/common.py
tests/whimsylib/__init__.py
tests/whimsylib/actor_test.py
tests/whimsylib/ai_test.py
tests/whimsylib/bag_test.py
tests/whimsylib/dice_test.py
tests/whimsylib/directions_test.py
tests/whimsylib/event_test.py
tests/whimsylib/globals_test.py
tests/whimsylib/item_test.py
tests/whimsylib/say_test.py
tests/whimsylib/when_test.py
whimsylib/__init__.py
whimsylib/actor.py
whimsylib/ai.py
whimsylib/bag.py
whimsylib/dice.py
whimsylib/directions.py
whimsylib/event.py
whimsylib/globals.py
whimsylib/item.py
whimsylib/room.py
whimsylib/say.py
whimsylib/start.py
whimsylib/tartarus.py
whimsylib/when.py
whimsylib/zalgo.py
whimsylib-1.4.2.dist-info/LICENSE
whimsylib-1.4.2.dist-info/METADATA
whimsylib-1.4.2.dist-info/WHEEL
whimsylib-1.4.2.dist-info/top_level.txt
whimsylib-1.4.2.dist-info/RECORD
