Metadata-Version: 2.1
Name: whimsylib
Version: 1.4.2
Summary: A generic game engine for text-based games, inspired by adventurelib.
Home-page: https://github.com/Cronenbrogues/whimsylib
Author: The Arch Cronenbrogues
Author-email: cronenbrogues@googlegroups.com
License: UNKNOWN
Platform: UNKNOWN
Requires-Python: >=3.8
